foliage/__init__.py
foliage/__main__.py
foliage/base_tab.py
foliage/change_tab.py
foliage/clean_tab.py
foliage/credentials.py
foliage/delete_tab.py
foliage/enum_utils.py
foliage/exceptions.py
foliage/export.py
foliage/folio.py
foliage/list_tab.py
foliage/lookup_tab.py
foliage/other_tab.py
foliage/system_widget.py
foliage/ui.py
foliage-1.7.2.dist-info/LICENSE
foliage-1.7.2.dist-info/METADATA
foliage-1.7.2.dist-info/WHEEL
foliage-1.7.2.dist-info/entry_points.txt
foliage-1.7.2.dist-info/top_level.txt
foliage-1.7.2.dist-info/RECORD
