Metadata-Version: 2.1
Name: foliage
Version: 1.7.2
Summary: Foliage: a tool to do bulk changes in FOLIO using the OKAPI API
Home-page: https://github.com/caltechlibrary/foliage
Author: Mike Hucka
Author-email: helpdesk@library.caltech.edu
License: BSD 3-clause license
Project-URL: Source Code, https://github.com/caltechlibrary/foliage
Project-URL: Bug Tracker, https://github.com/caltechlibrary/foliage/issues
Keywords: Python,applications
Classifier: Development Status :: 5 - Production/Stable
Classifier: Environment :: Console
Classifier: License :: OSI Approved :: BSD License
Classifier: Intended Audience :: Science/Research
Classifier: Operating System :: MacOS :: MacOS X
Classifier: Operating System :: POSIX
Classifier: Operating System :: POSIX :: Linux
Classifier: Operating System :: Unix
Classifier: Programming Language :: Python
Classifier: Programming Language :: Python :: 3.9
Requires-Python: >=3.9
License-File: LICENSE
Requires-Dist: appdirs (==1.4.4)
Requires-Dist: boltons (==21.0.0)
Requires-Dist: commonpy (==1.13.0)
Requires-Dist: fastnumbers (==3.1.0)
Requires-Dist: keyring (==23.2.1)
Requires-Dist: openpyxl (==3.0.7)
Requires-Dist: plac (==1.3.4)
Requires-Dist: pyperclip (==1.8.2)
Requires-Dist: PyQt5 (==5.15.9)
Requires-Dist: python-decouple (==3.5)
Requires-Dist: python-dateutil (==2.8.2)
Requires-Dist: rich (>=13.3.5)
Requires-Dist: setuptools
Requires-Dist: sidetrack (>=2.0.1)
Requires-Dist: tornado (==6.1)
Requires-Dist: python-slugify (==8.0.1)
Requires-Dist: validators (==0.20.0)
Requires-Dist: wand (==0.6.11)
Provides-Extra: dev
Requires-Dist: appdirs (==1.4.4) ; extra == 'dev'
Requires-Dist: boltons (==21.0.0) ; extra == 'dev'
Requires-Dist: commonpy (==1.13.0) ; extra == 'dev'
Requires-Dist: fastnumbers (==3.1.0) ; extra == 'dev'
Requires-Dist: keyring (==23.2.1) ; extra == 'dev'
Requires-Dist: openpyxl (==3.0.7) ; extra == 'dev'
Requires-Dist: plac (==1.3.4) ; extra == 'dev'
Requires-Dist: pyperclip (==1.8.2) ; extra == 'dev'
Requires-Dist: PyQt5 (==5.15.9) ; extra == 'dev'
Requires-Dist: python-decouple (==3.5) ; extra == 'dev'
Requires-Dist: python-dateutil (==2.8.2) ; extra == 'dev'
Requires-Dist: rich (>=13.3.5) ; extra == 'dev'
Requires-Dist: setuptools ; extra == 'dev'
Requires-Dist: sidetrack (>=2.0.1) ; extra == 'dev'
Requires-Dist: tornado (==6.1) ; extra == 'dev'
Requires-Dist: python-slugify (==8.0.1) ; extra == 'dev'
Requires-Dist: validators (==0.20.0) ; extra == 'dev'
Requires-Dist: wand (==0.6.11) ; extra == 'dev'
Requires-Dist: pytest (>=6.2.5) ; extra == 'dev'
Requires-Dist: pytest-cov (>=3.0.0) ; extra == 'dev'
Requires-Dist: pytest-mock (>=3.7.0) ; extra == 'dev'
Requires-Dist: flake8 (>=4.0.1) ; extra == 'dev'
Requires-Dist: flake8-bugbear (>=22.4.25) ; extra == 'dev'
Requires-Dist: flake8-builtins (>=1.5.3) ; extra == 'dev'
Requires-Dist: flake8-comprehensions (>=3.8.0) ; extra == 'dev'
Requires-Dist: flake8-executable (>=2.1.1) ; extra == 'dev'
Requires-Dist: flake8-implicit-str-concat (>=0.3.0) ; extra == 'dev'
Requires-Dist: flake8-pie (>=0.15.0) ; extra == 'dev'
Requires-Dist: flake8-simplify (>=0.19.2) ; extra == 'dev'
Requires-Dist: pyinstaller ; extra == 'dev'
Requires-Dist: linkify-it-py ; extra == 'dev'
Requires-Dist: myst-parser ; extra == 'dev'
Requires-Dist: sphinx-autobuild ; extra == 'dev'
Requires-Dist: sphinx-material ; extra == 'dev'
Requires-Dist: sphinxcontrib-mermaid ; extra == 'dev'
Requires-Dist: twine ; extra == 'dev'
Requires-Dist: wheel ; extra == 'dev'
